setup.py
StackSentinel/__init__.py
stacksentinel.egg-info/PKG-INFO
stacksentinel.egg-info/SOURCES.txt
stacksentinel.egg-info/dependency_links.txt
stacksentinel.egg-info/top_level.txt