Metadata-Version: 1.1
Name: stacksentinel
Version: 1.2.1
Summary: Stack Sentinel client and WSGI middleware
Home-page: https://github.com/StackSentinel/stacksentinel-python
Author: Jeri MgCuckin
Author-email: jerymcguckin@stacksentinel.com
License: Apache License (2.0)
Keywords: stack sentinel stacksentinel exception tracking api
Platform: UNKNOWN
Classifier: Programming Language :: Python
Classifier: Programming Language :: Python :: 2
Classifier: Programming Language :: Python :: 2.7
Classifier: Programming Language :: Python :: 3
Classifier: Programming Language :: Python :: 3.4
Classifier: Operating System :: OS Independent
Classifier: Programming Language :: Python
Classifier: Intended Audience :: Developers
